LICENSE
MANIFEST.in
README.rst
setup.cfg
setup.py
tests/__init__.py
tests/test_core.py
tests/test_expressions.py
tests/test_processors.py
tests/test_summary.py
tests/test_utils.py
typus/__init__.py
typus/chars.py
typus/core.py
typus/utils.py
typus.egg-info/PKG-INFO
typus.egg-info/SOURCES.txt
typus.egg-info/dependency_links.txt
typus.egg-info/top_level.txt
typus/processors/__init__.py
typus/processors/base.py
typus/processors/escapes.py
typus/processors/expressions.py
typus/processors/quotes.py